grus/__init__.py
grus-0.0.1.dist-info/LICENSE
grus-0.0.1.dist-info/METADATA
grus-0.0.1.dist-info/WHEEL
grus-0.0.1.dist-info/top_level.txt
grus-0.0.1.dist-info/RECORD
